[{
  "_id": 1,
  "invoice_number": 1,
  "description": "Implemented mission-critical support",
  "bill_to": "Luise Ridsdale",
  "address": {
    "street": "6984 Surrey Center",
    "city": "Yerevan",
    "full_address": "6984 Surrey Center, Yerevan"
  },
  "billing_address": 60,
  "amount": 249.69,
  "due_date": "08/08/2023",
  "status": "Pending",
  "items": [
    {
      "item_name": "ligula in lacus curabitur",
      "quantity": 2,
      "price": 71
    }
  ]
}, {
  "_id": 2,
  "invoice_number": 2,
  "description": "Pre-emptive content-based matrix",
  "bill_to": "Wrennie Willmont",
  "address": {
    "street": "6 Delladonna Pass",
    "city": "Cortezia",
    "full_address": "6 Delladonna Pass, Cortezia"
  },
  "billing_address": 44,
  "amount": 543.5,
  "due_date": "10/23/2023",
  "status": "Draft",
  "items": [
    {
      "item_name": "sollicitudin mi sit amet lobortis",
      "quantity": 9,
      "price": 41
    },
    {
      "item_name": "integer ac neque duis bibendum morbi non quam",
      "quantity": 3,
      "price": 66
    },
    {
      "item_name": "faucibus accumsan odio curabitur",
      "quantity": 9,
      "price": 56
    },
    {
      "item_name": "velit nec nisi vulputate nonummy maecenas tincidunt",
      "quantity": 2,
      "price": 23
    }
  ]
}, {
  "_id": 3,
  "invoice_number": 3,
  "description": "Horizontal encompassing forecast",
  "bill_to": "Noel Woodnutt",
  "address": {
    "street": "14564 Warrior Circle",
    "city": "Ubon Ratchathani",
    "full_address": "14564 Warrior Circle, Ubon Ratchathani"
  },
  "billing_address": 88,
  "amount": 445.47,
  "due_date": "12/19/2023",
  "status": "Draft",
  "items": [
    {
      "item_name": "tristique est et tempus semper est quam",
      "quantity": 10,
      "price": 26
    },
    {
      "item_name": "lacus at velit vivamus vel nulla",
      "quantity": 8,
      "price": 66
    }
  ]
}, {
  "_id": 4,
  "invoice_number": 4,
  "description": "Multi-channelled transitional groupware",
  "bill_to": "Editha Rubanenko",
  "address": {
    "street": "4441 Montana Hill",
    "city": "Yurla",
    "full_address": "4441 Montana Hill, Yurla"
  },
  "billing_address": 48,
  "amount": 980.42,
  "due_date": "02/19/2024",
  "status": "Draft",
  "items": [
    {
      "item_name": "erat quisque erat eros viverra eget congue eget semper",
      "quantity": 6,
      "price": 47
    }
  ]
}, {
  "_id": 5,
  "invoice_number": 5,
  "description": "Extended content-based software",
  "bill_to": "Rivkah Haily",
  "address": {
    "street": "6 Milwaukee Drive",
    "city": "Banzão",
    "full_address": "6 Milwaukee Drive, Banzão"
  },
  "billing_address": 93,
  "amount": 826.52,
  "due_date": "03/31/2023",
  "status": "Pending",
  "items": [
    {
      "item_name": "augue quam sollicitudin vitae consectetuer",
      "quantity": 1,
      "price": 56
    }
  ]
}, {
  "_id": 6,
  "invoice_number": 6,
  "description": "Universal heuristic projection",
  "bill_to": "Auroora Dankov",
  "address": {
    "street": "36278 Elka Point",
    "city": "Khasavyurt",
    "full_address": "36278 Elka Point, Khasavyurt"
  },
  "billing_address": 85,
  "amount": 619.84,
  "due_date": "06/24/2023",
  "status": "Pending",
  "items": [
    {
      "item_name": "aliquam convallis nunc proin at turpis a pede",
      "quantity": 1,
      "price": 90
    },
    {
      "item_name": "est congue elementum in",
      "quantity": 6,
      "price": 61
    }
  ]
}, {
  "_id": 7,
  "invoice_number": 7,
  "description": "Advanced 24/7 attitude",
  "bill_to": "Taber Karppi",
  "address": {
    "street": "54974 Mosinee Terrace",
    "city": "Pignon",
    "full_address": "54974 Mosinee Terrace, Pignon"
  },
  "billing_address": 38,
  "amount": 259.07,
  "due_date": "06/13/2023",
  "status": "Paid",
  "items": [
    {
      "item_name": "tempor convallis nulla neque libero convallis eget eleifend",
      "quantity": 3,
      "price": 92
    },
    {
      "item_name": "integer ac neque duis bibendum",
      "quantity": 5,
      "price": 97
    },
    {
      "item_name": "morbi quis tortor id nulla ultrices",
      "quantity": 9,
      "price": 98
    },
    {
      "item_name": "erat tortor sollicitudin mi sit",
      "quantity": 7,
      "price": 37
    }
  ]
}, {
  "_id": 8,
  "invoice_number": 8,
  "description": "Phased scalable archive",
  "bill_to": "Hasheem Esp",
  "address": {
    "street": "092 Basil Trail",
    "city": "Bāfq",
    "full_address": "092 Basil Trail, Bāfq"
  },
  "billing_address": 55,
  "amount": 488.92,
  "due_date": "09/04/2023",
  "status": "Pending",
  "items": [
    {
      "item_name": "vitae ipsum aliquam non mauris morbi non lectus aliquam sit",
      "quantity": 6,
      "price": 48
    }
  ]
}, {
  "_id": 9,
  "invoice_number": 9,
  "description": "Team-oriented hybrid workforce",
  "bill_to": "Loutitia Soldan",
  "address": {
    "street": "942 Mariners Cove Trail",
    "city": "Virojoki",
    "full_address": "942 Mariners Cove Trail, Virojoki"
  },
  "billing_address": 80,
  "amount": 846.22,
  "due_date": "05/20/2024",
  "status": "Paid",
  "items": [
    {
      "item_name": "in faucibus orci luctus",
      "quantity": 10,
      "price": 11
    }
  ]
}, {
  "_id": 10,
  "invoice_number": 10,
  "description": "Inverse discrete standardization",
  "bill_to": "Weylin Eeles",
  "address": {
    "street": "984 Boyd Terrace",
    "city": "Akademija (Kaunas)",
    "full_address": "984 Boyd Terrace, Akademija (Kaunas)"
  },
  "billing_address": 82,
  "amount": 959.52,
  "due_date": "03/16/2023",
  "status": "Draft",
  "items": [
    {
      "item_name": "pharetra magna ac consequat metus sapien ut",
      "quantity": 7,
      "price": 37
    },
    {
      "item_name": "venenatis non sodales sed tincidunt eu felis fusce",
      "quantity": 3,
      "price": 68
    },
    {
      "item_name": "amet consectetuer adipiscing elit proin interdum mauris non ligula pellentesque",
      "quantity": 5,
      "price": 41
    },
    {
      "item_name": "nulla integer pede justo lacinia",
      "quantity": 6,
      "price": 12
    },
    {
      "item_name": "nibh ligula nec sem duis aliquam convallis nunc proin",
      "quantity": 9,
      "price": 79
    }
  ]
}, {
  "_id": 11,
  "invoice_number": 11,
  "description": "Focused real-time definition",
  "bill_to": "Giacopo Sparke",
  "address": {
    "street": "2 Hintze Hill",
    "city": "Mahdia",
    "full_address": "2 Hintze Hill, Mahdia"
  },
  "billing_address": 75,
  "amount": 971.65,
  "due_date": "01/16/2024",
  "status": "Paid",
  "items": [
    {
      "item_name": "et magnis dis parturient",
      "quantity": 8,
      "price": 84
    },
    {
      "item_name": "viverra pede ac diam",
      "quantity": 2,
      "price": 26
    },
    {
      "item_name": "morbi quis tortor id nulla ultrices aliquet maecenas",
      "quantity": 10,
      "price": 72
    },
    {
      "item_name": "libero non mattis pulvinar nulla pede ullamcorper augue a suscipit",
      "quantity": 2,
      "price": 11
    },
    {
      "item_name": "cursus urna ut tellus nulla ut erat id",
      "quantity": 1,
      "price": 84
    }
  ]
}, {
  "_id": 12,
  "invoice_number": 12,
  "description": "Expanded scalable matrix",
  "bill_to": "Denys Schirak",
  "address": {
    "street": "35356 Meadow Vale Crossing",
    "city": "Kefang",
    "full_address": "35356 Meadow Vale Crossing, Kefang"
  },
  "billing_address": 59,
  "amount": 424.98,
  "due_date": "04/13/2023",
  "status": "Paid",
  "items": [
    {
      "item_name": "praesent blandit lacinia erat vestibulum sed",
      "quantity": 8,
      "price": 59
    },
    {
      "item_name": "nulla mollis molestie lorem quisque ut erat curabitur gravida nisi",
      "quantity": 3,
      "price": 84
    },
    {
      "item_name": "nisi eu orci mauris lacinia sapien",
      "quantity": 2,
      "price": 49
    },
    {
      "item_name": "auctor sed tristique in tempus sit amet",
      "quantity": 4,
      "price": 75
    },
    {
      "item_name": "fusce posuere felis sed lacus morbi",
      "quantity": 1,
      "price": 55
    }
  ]
}, {
  "_id": 13,
  "invoice_number": 13,
  "description": "Networked asymmetric time-frame",
  "bill_to": "Kip Paolillo",
  "address": {
    "street": "4393 Bultman Hill",
    "city": "Yinglong",
    "full_address": "4393 Bultman Hill, Yinglong"
  },
  "billing_address": 22,
  "amount": 231.58,
  "due_date": "11/30/2023",
  "status": "Pending",
  "items": [
    {
      "item_name": "nulla sed vel enim sit amet",
      "quantity": 4,
      "price": 75
    },
    {
      "item_name": "est phasellus sit amet",
      "quantity": 5,
      "price": 92
    }
  ]
}, {
  "_id": 14,
  "invoice_number": 14,
  "description": "Horizontal dedicated interface",
  "bill_to": "Burke Ortes",
  "address": {
    "street": "390 Huxley Parkway",
    "city": "Kalmar",
    "full_address": "390 Huxley Parkway, Kalmar"
  },
  "billing_address": 33,
  "amount": 699.01,
  "due_date": "12/21/2022",
  "status": "Pending",
  "items": [
    {
      "item_name": "felis sed lacus morbi sem mauris laoreet ut",
      "quantity": 10,
      "price": 17
    },
    {
      "item_name": "eu magna vulputate luctus",
      "quantity": 5,
      "price": 76
    },
    {
      "item_name": "sem mauris laoreet ut rhoncus aliquet pulvinar sed",
      "quantity": 1,
      "price": 14
    },
    {
      "item_name": "erat fermentum justo nec condimentum neque sapien placerat ante",
      "quantity": 7,
      "price": 38
    },
    {
      "item_name": "non lectus aliquam sit amet diam in",
      "quantity": 2,
      "price": 44
    }
  ]
}, {
  "_id": 15,
  "invoice_number": 15,
  "description": "Object-based transitional groupware",
  "bill_to": "Nickey Hickenbottom",
  "address": {
    "street": "278 Hanover Court",
    "city": "Las Parejas",
    "full_address": "278 Hanover Court, Las Parejas"
  },
  "billing_address": 99,
  "amount": 402.02,
  "due_date": "12/10/2023",
  "status": "Draft",
  "items": [
    {
      "item_name": "lacus morbi sem mauris",
      "quantity": 1,
      "price": 76
    },
    {
      "item_name": "sagittis nam congue risus semper porta",
      "quantity": 9,
      "price": 25
    },
    {
      "item_name": "hac habitasse platea dictumst morbi vestibulum",
      "quantity": 3,
      "price": 68
    },
    {
      "item_name": "lacinia sapien quis libero nullam",
      "quantity": 4,
      "price": 30
    },
    {
      "item_name": "ligula suspendisse ornare consequat lectus in est",
      "quantity": 1,
      "price": 67
    }
  ]
}, {
  "_id": 16,
  "invoice_number": 16,
  "description": "Secured bottom-line software",
  "bill_to": "Margaretha Bonanno",
  "address": {
    "street": "83 Mcguire Hill",
    "city": "Zhonghualu",
    "full_address": "83 Mcguire Hill, Zhonghualu"
  },
  "billing_address": 91,
  "amount": 918.58,
  "due_date": "03/03/2024",
  "status": "Paid",
  "items": [
    {
      "item_name": "integer non velit donec diam neque vestibulum eget vulputate ut",
      "quantity": 6,
      "price": 20
    },
    {
      "item_name": "ultricies eu nibh quisque id",
      "quantity": 3,
      "price": 78
    },
    {
      "item_name": "eleifend quam a odio in hac habitasse platea dictumst",
      "quantity": 9,
      "price": 11
    },
    {
      "item_name": "adipiscing lorem vitae mattis nibh ligula nec",
      "quantity": 9,
      "price": 44
    }
  ]
}, {
  "_id": 17,
  "invoice_number": 17,
  "description": "Synergized modular functionalities",
  "bill_to": "Devin Coda",
  "address": {
    "street": "5 Thierer Lane",
    "city": "Trần Văn Thời",
    "full_address": "5 Thierer Lane, Trần Văn Thời"
  },
  "billing_address": 48,
  "amount": 342.34,
  "due_date": "11/19/2023",
  "status": "Draft",
  "items": [
    {
      "item_name": "sapien sapien non mi integer ac",
      "quantity": 7,
      "price": 63
    },
    {
      "item_name": "nulla justo aliquam quis",
      "quantity": 9,
      "price": 10
    }
  ]
}, {
  "_id": 18,
  "invoice_number": 18,
  "description": "Organized real-time moratorium",
  "bill_to": "Glyn Rhead",
  "address": {
    "street": "70 Farwell Drive",
    "city": "Hagfors",
    "full_address": "70 Farwell Drive, Hagfors"
  },
  "billing_address": 66,
  "amount": 214.84,
  "due_date": "12/11/2022",
  "status": "Pending",
  "items": [
    {
      "item_name": "in ante vestibulum ante",
      "quantity": 7,
      "price": 89
    }
  ]
}, {
  "_id": 19,
  "invoice_number": 19,
  "description": "Cross-group motivating success",
  "bill_to": "Chandra Furst",
  "address": {
    "street": "832 Fieldstone Center",
    "city": "Las Lajas",
    "full_address": "832 Fieldstone Center, Las Lajas"
  },
  "billing_address": 60,
  "amount": 950.26,
  "due_date": "01/17/2024",
  "status": "Draft",
  "items": [
    {
      "item_name": "etiam pretium iaculis justo in hac habitasse platea",
      "quantity": 3,
      "price": 92
    },
    {
      "item_name": "turpis adipiscing lorem vitae mattis nibh ligula",
      "quantity": 9,
      "price": 53
    },
    {
      "item_name": "libero non mattis pulvinar nulla pede ullamcorper augue a suscipit",
      "quantity": 1,
      "price": 77
    },
    {
      "item_name": "nunc commodo placerat praesent blandit nam",
      "quantity": 5,
      "price": 17
    },
    {
      "item_name": "quis lectus suspendisse potenti in eleifend quam a odio in",
      "quantity": 7,
      "price": 92
    }
  ]
}, {
  "_id": 20,
  "invoice_number": 20,
  "description": "Optional empowering support",
  "bill_to": "Ashton Champe",
  "address": {
    "street": "64397 Bonner Hill",
    "city": "Cruzeiro",
    "full_address": "64397 Bonner Hill, Cruzeiro"
  },
  "billing_address": 57,
  "amount": 621.43,
  "due_date": "01/03/2023",
  "status": "Draft",
  "items": [
    {
      "item_name": "id consequat in consequat ut nulla sed accumsan",
      "quantity": 9,
      "price": 79
    }
  ]
}]